api_queries/__init__.py
utils/__init__.py
utils/vscode.py
git_init_repo-1.0.2.dist-info/LICENSE
git_init_repo-1.0.2.dist-info/METADATA
git_init_repo-1.0.2.dist-info/WHEEL
git_init_repo-1.0.2.dist-info/top_level.txt
git_init_repo-1.0.2.dist-info/RECORD
