Metadata-Version: 2.1
Name: git-init-repo
Version: 1.0.2
Summary: A Python script to initialize a git repository.
Author: Thomas "Aiglon Dore" R.
Author-email: aiglondore@outlook.com
License-File: LICENSE
Requires-Dist: aiohttp
